globza/IoF_browser.py
globza/__init__.py
globza/print_pretty.py
Globza-2.0.3.dist-info/LICENSE.txt
Globza-2.0.3.dist-info/METADATA
Globza-2.0.3.dist-info/WHEEL
Globza-2.0.3.dist-info/requirements.txt
Globza-2.0.3.dist-info/top_level.txt
Globza-2.0.3.dist-info/RECORD
