Metadata-Version: 2.1
Name: Globza
Version: 2.0.3
Summary: Browser to interact with the universal IOF (Internet of Functions) service
Author: Sergei Sychev
Author-email: sch@triz-ri.com
License: Proprietary
License-File: LICENSE.txt
Requires-Dist: requests
